{
    "fluentMethods": true,
    "relationships": [
        {
            "relationshipType": "one-to-one",
            "relationshipValidateRules": "required",
            "relationshipName": "author",
            "otherEntityName": "user",
            "otherEntityField": "id",
            "ownerSide": true,
            "otherEntityRelationshipName": "category"
        },
        {
            "relationshipName": "message",
            "otherEntityName": "message",
            "relationshipType": "many-to-one",
            "otherEntityField": "id"
        }
    ],
    "fields": [
        {
            "fieldName": "title",
            "fieldType": "String",
            "fieldValidateRules": [
                "required"
            ]
        },
        {
            "fieldName": "description",
            "fieldType": "String",
            "fieldValidateRules": [
                "required"
            ]
        },
        {
            "fieldName": "imagen",
            "fieldType": "byte[]",
            "fieldTypeBlobContent": "any",
            "fieldValidateRules": [
                "required"
            ]
        }
    ],
    "changelogDate": "20180510152033",
    "entityTableName": "category",
    "dto": "no",
    "pagination": "no",
    "service": "no",
    "jpaMetamodelFiltering": false
}